odoo/addons/stock_account_prepare_anglo_saxon_out_lines_hook/README.rst
odoo/addons/stock_account_prepare_anglo_saxon_out_lines_hook/__init__.py
odoo/addons/stock_account_prepare_anglo_saxon_out_lines_hook/__manifest__.py
odoo/addons/stock_account_prepare_anglo_saxon_out_lines_hook/hooks.py
odoo/addons/stock_account_prepare_anglo_saxon_out_lines_hook/i18n/stock_account_prepare_anglo_saxon_out_lines_hook.pot
odoo/addons/stock_account_prepare_anglo_saxon_out_lines_hook/models/__init__.py
odoo/addons/stock_account_prepare_anglo_saxon_out_lines_hook/models/account_move.py
odoo/addons/stock_account_prepare_anglo_saxon_out_lines_hook/models/account_move_line.py
odoo/addons/stock_account_prepare_anglo_saxon_out_lines_hook/static/description/icon.png
odoo13_addon_stock_account_prepare_anglo_saxon_out_lines_hook-13.0.1.0.4.dist-info/METADATA
odoo13_addon_stock_account_prepare_anglo_saxon_out_lines_hook-13.0.1.0.4.dist-info/WHEEL
odoo13_addon_stock_account_prepare_anglo_saxon_out_lines_hook-13.0.1.0.4.dist-info/top_level.txt
odoo13_addon_stock_account_prepare_anglo_saxon_out_lines_hook-13.0.1.0.4.dist-info/RECORD
